cads_sdk/__init__.py
cads_sdk/id_card/__init__.py
cads_sdk/id_card/display.py
cads_sdk/nosql/__init__.py
cads_sdk/nosql/codec.py
cads_sdk/nosql/converter.py
cads_sdk/nosql/display.py
cads_sdk/nosql/etl.py
cads_sdk/nosql/utils.py
cads_sdk/petastorm/__init__.py
cads_sdk/petastorm/dataset_metadata.py
cads_sdk/petastorm/fs_utils.py
cads_sdk/petastorm/utils.py
cads_sdk/pytorch/__init__.py
cads_sdk/pytorch/codec.py
cads_sdk/pytorch/converter.py
cads_sdk-0.0.28.dist-info/METADATA
cads_sdk-0.0.28.dist-info/WHEEL
cads_sdk-0.0.28.dist-info/top_level.txt
cads_sdk-0.0.28.dist-info/RECORD
