Metadata-Version: 2.1
Name: cads_sdk
Version: 0.0.28
Summary: Function to help Data Scientist work more effectively with DWH
Home-page: http://git.bigdata.local/data-engineers/sdk/utilities
Author: duyvnc
Author-email: duyvnc@fpt.com.vn
License: duyvnc
Requires-Python: >=3.5
Requires-Dist: spark-sdk (>=0.4.23)
Requires-Dist: opencv-python
Requires-Dist: Pillow
Requires-Dist: scipy
Requires-Dist: pydub
Requires-Dist: ipywidgets
Requires-Dist: petastorm
